cca/__init__.py
cca/cca.py
cca/chaimcli.py
cca/cliinifile.py
cca/cliutils.py
chaim_cli-2.5.3.dist-info/LICENSE
chaim_cli-2.5.3.dist-info/METADATA
chaim_cli-2.5.3.dist-info/WHEEL
chaim_cli-2.5.3.dist-info/entry_points.txt
chaim_cli-2.5.3.dist-info/top_level.txt
chaim_cli-2.5.3.dist-info/RECORD
